{
    "898b486a-53ab-c7ac-d958-a0bf97f67f29": {
        "paletteKey": "FlexLayoutCol",
        "commentid": null,
        "designerReference": [
            {
                "_key": "componentLabel",
                "_value": "Column",
                "_type": "kv",
                "_attrDef": "p",
                "_useAsLabel": true
            },
            {
                "_key": "style",
                "_value": "",
                "_type": "kv",
                "_attrDef": "p"
            },
            {
                "_key": "class",
                "_value": [
                    "height-100"
                ],
                "_type": "dav",
                "_attrDef": "p"
            },
            {
                "_key": "fxFlex",
                "_value": "",
                "_type": "kv",
                "_attrDef": "p"
            },
            {
                "_key": "fxLayoutGap",
                "_value": "1rem",
                "_type": "kv",
                "_attrDef": "p"
            },
            {
                "_key": "wrap",
                "_value": "wrap",
                "_type": "a",
                "_attrDef": "p"
            },
            {
                "_key": "layoutAlign",
                "_value": "start",
                "_type": "a",
                "_attrDef": "p"
            },
            {
                "_key": "pLayoutAlign",
                "_value": "stretch",
                "_type": "a",
                "_attrDef": "p"
            },
            {
                "_key": "[fxShow]",
                "_value": "true",
                "_type": "kv",
                "_attrDef": "p"
            }
        ],
        "64b528db-2236-fac4-69ce-70f0245e4f78": {
            "paletteKey": "ad-card",
            "parentEditorKey": "898b486a-53ab-c7ac-d958-a0bf97f67f29",
            "isAdvancedComponent": true,
            "commentid": null,
            "designerReference": [
                {
                    "_key": "componentLabel",
                    "_value": "Card",
                    "_type": "kv",
                    "_attrDef": "p",
                    "_useAsLabel": true
                },
                {
                    "_key": "style",
                    "_value": "",
                    "_type": "kv",
                    "_attrDef": "p"
                },
                {
                    "_key": "class",
                    "_value": [
                        "personal-details-card",
                        "height-100"
                    ],
                    "_type": "dav",
                    "_attrDef": "p"
                },
                {
                    "_key": "tabindex",
                    "_value": "",
                    "_type": "kv",
                    "_attrDef": "p"
                }
            ],
            "f32c5c3b-1980-006b-c078-bec7d34fa2aa": {
                "paletteKey": "ng-card-content",
                "parentEditorKey": "64b528db-2236-fac4-69ce-70f0245e4f78",
                "isAdvancedChildComponent": true,
                "commentid": null,
                "designerReference": [
                    {
                        "_key": "style",
                        "_value": "",
                        "_type": "kv",
                        "_attrDef": "p"
                    },
                    {
                        "_key": "class",
                        "_value": [
                            "height-100"
                        ],
                        "_type": "dav",
                        "_attrDef": "p"
                    },
                    {
                        "_key": "align",
                        "_value": "",
                        "_type": "kv",
                        "_attrDef": "p"
                    }
                ],
                "a35f3fd1-9006-84c9-7852-3a054b061809": {
                    "paletteKey": "FlexLayoutCol",
                    "parentEditorKey": "f32c5c3b-1980-006b-c078-bec7d34fa2aa",
                    "commentid": null,
                    "designerReference": [
                        {
                            "_key": "componentLabel",
                            "_value": "Column",
                            "_type": "kv",
                            "_attrDef": "p",
                            "_useAsLabel": true
                        },
                        {
                            "_key": "style",
                            "_value": "",
                            "_type": "kv",
                            "_attrDef": "p"
                        },
                        {
                            "_key": "class",
                            "_value": [
                                "padding-1",
                                "height-100"
                            ],
                            "_type": "dav",
                            "_attrDef": "p"
                        },
                        {
                            "_key": "fxFlex",
                            "_value": "",
                            "_type": "kv",
                            "_attrDef": "p"
                        },
                        {
                            "_key": "fxLayoutGap",
                            "_value": "2rem",
                            "_type": "kv",
                            "_attrDef": "p"
                        },
                        {
                            "_key": "wrap",
                            "_value": "",
                            "_type": "a",
                            "_attrDef": "p"
                        },
                        {
                            "_key": "layoutAlign",
                            "_value": "start",
                            "_type": "a",
                            "_attrDef": "p"
                        },
                        {
                            "_key": "pLayoutAlign",
                            "_value": "stretch",
                            "_type": "a",
                            "_attrDef": "p"
                        },
                        {
                            "_key": "[fxShow]",
                            "_value": "true",
                            "_type": "kv",
                            "_attrDef": "p"
                        }
                    ],
                    "ee14fc7e-08b2-710b-6f33-6f47f2d06c60": {
                        "paletteKey": "FlexLayoutRow",
                        "parentEditorKey": "a35f3fd1-9006-84c9-7852-3a054b061809",
                        "commentid": null,
                        "designerReference": [
                            {
                                "_key": "componentLabel",
                                "_value": "Row",
                                "_type": "kv",
                                "_attrDef": "p",
                                "_useAsLabel": true
                            },
                            {
                                "_key": "style",
                                "_value": "",
                                "_type": "kv",
                                "_attrDef": "p"
                            },
                            {
                                "_key": "class",
                                "_value": "",
                                "_type": "dav",
                                "_attrDef": "p"
                            },
                            {
                                "_key": "fxFlex",
                                "_value": "",
                                "_type": "kv",
                                "_attrDef": "p"
                            },
                            {
                                "_key": "fxLayoutGap",
                                "_value": "1rem",
                                "_type": "kv",
                                "_attrDef": "p"
                            },
                            {
                                "_key": "wrap",
                                "_value": "",
                                "_type": "a",
                                "_attrDef": "p"
                            },
                            {
                                "_key": "layoutAlign",
                                "_value": "start",
                                "_type": "a",
                                "_attrDef": "p"
                            },
                            {
                                "_key": "pLayoutAlign",
                                "_value": "center",
                                "_type": "a",
                                "_attrDef": "p"
                            },
                            {
                                "_key": "[fxShow]",
                                "_value": "true",
                                "_type": "kv",
                                "_attrDef": "p"
                            }
                        ],
                        "5ad917ee-db73-14aa-a1ca-299e963e8b43": {
                            "paletteKey": "NG-image",
                            "parentEditorKey": "ee14fc7e-08b2-710b-6f33-6f47f2d06c60",
                            "commentid": null,
                            "designerReference": [
                                {
                                    "_key": "componentLabel",
                                    "_value": "Image",
                                    "_type": "kv",
                                    "_attrDef": "p",
                                    "_useAsLabel": true
                                },
                                {
                                    "_key": "style",
                                    "_value": "",
                                    "_type": "kv",
                                    "_attrDef": "p"
                                },
                                {
                                    "_key": "class",
                                    "_value": "",
                                    "_type": "dav",
                                    "_attrDef": "p"
                                },
                                {
                                    "_key": "imgSrc",
                                    "_value": "",
                                    "_type": "kv",
                                    "_attrDef": "p"
                                },
                                {
                                    "_key": "alt",
                                    "_value": "",
                                    "_type": "kv",
                                    "_attrDef": "p"
                                },
                                {
                                    "_key": "[src]",
                                    "_value": "data?.viewIconName",
                                    "_type": "kv",
                                    "_attrDef": "p"
                                },
                                {
                                    "_key": "imgSecure",
                                    "_value": "",
                                    "_type": "a",
                                    "_attrDef": "p"
                                },
                                {
                                    "_key": "width",
                                    "_value": "",
                                    "_type": "kv",
                                    "_attrDef": "p"
                                },
                                {
                                    "_key": "srcset",
                                    "_value": "",
                                    "_type": "kv",
                                    "_attrDef": "p"
                                },
                                {
                                    "_key": "sizes",
                                    "_value": "",
                                    "_type": "kv",
                                    "_attrDef": "p"
                                }
                            ]
                        },
                        "69b6f07f-6165-dc98-0e75-e218e6a04483": {
                            "paletteKey": "Html5",
                            "parentEditorKey": "ee14fc7e-08b2-710b-6f33-6f47f2d06c60",
                            "isAdvancedComponent": true,
                            "commentid": null,
                            "designerReference": [
                                {
                                    "_key": "style",
                                    "_value": "",
                                    "_type": "kv",
                                    "_attrDef": "p"
                                },
                                {
                                    "_key": "class",
                                    "_value": [
                                        "margin-0"
                                    ],
                                    "_type": "dav",
                                    "_attrDef": "p"
                                },
                                {
                                    "_key": "htmlElement",
                                    "_value": "mat-card-title",
                                    "_type": "dav",
                                    "_attrDef": "p",
                                    "_useAsLabel": true,
                                    "_customAttributeFlag": "customInput"
                                },
                                {
                                    "_key": "tagType",
                                    "_value": "mat-card-title",
                                    "_type": "a",
                                    "_attrDef": "p",
                                    "_visibility": false
                                },
                                {
                                    "_key": "name",
                                    "_value": "",
                                    "_type": "kv",
                                    "_attrDef": "p",
                                    "_visibility": false
                                },
                                {
                                    "_key": "sandbox",
                                    "_value": "",
                                    "_type": "kv",
                                    "_attrDef": "p",
                                    "_visibility": false
                                },
                                {
                                    "_key": "src",
                                    "_value": "",
                                    "_type": "kv",
                                    "_attrDef": "p",
                                    "_visibility": false
                                },
                                {
                                    "_key": "srcdoc",
                                    "_value": "",
                                    "_type": "kv",
                                    "_attrDef": "p",
                                    "_visibility": false
                                },
                                {
                                    "_key": "width",
                                    "_value": "",
                                    "_type": "kv",
                                    "_attrDef": "p",
                                    "_visibility": false
                                },
                                {
                                    "_key": "[autoplay]",
                                    "_value": "",
                                    "_type": "kv",
                                    "_attrDef": "p",
                                    "_visibility": false
                                },
                                {
                                    "_key": "[loop]",
                                    "_value": "",
                                    "_type": "kv",
                                    "_attrDef": "p",
                                    "_visibility": false
                                },
                                {
                                    "_key": "data",
                                    "_value": "",
                                    "_type": "kv",
                                    "_attrDef": "p",
                                    "_visibility": false
                                },
                                {
                                    "_key": "audioSource",
                                    "_value": [],
                                    "_type": "a",
                                    "_attrDef": "p",
                                    "_visibility": false
                                },
                                {
                                    "_key": "videoSource",
                                    "_value": [],
                                    "_type": "a",
                                    "_attrDef": "p",
                                    "_visibility": false
                                },
                                {
                                    "_key": "audioDatasource",
                                    "_value": "",
                                    "_type": "a",
                                    "_attrDef": "p",
                                    "_visibility": false
                                },
                                {
                                    "_key": "audioSrc",
                                    "_value": "",
                                    "_type": "a",
                                    "_attrDef": "p",
                                    "_visibility": false
                                },
                                {
                                    "_key": "audioType",
                                    "_value": "",
                                    "_type": "a",
                                    "_attrDef": "p",
                                    "_visibility": false
                                },
                                {
                                    "_key": "videoDatasource",
                                    "_value": "",
                                    "_type": "a",
                                    "_attrDef": "p",
                                    "_visibility": false
                                },
                                {
                                    "_key": "videoSrc",
                                    "_value": "",
                                    "_type": "a",
                                    "_attrDef": "p",
                                    "_visibility": false
                                },
                                {
                                    "_key": "videoType",
                                    "_value": "",
                                    "_type": "a",
                                    "_attrDef": "p",
                                    "_visibility": false
                                },
                                {
                                    "_key": "(audioplay)",
                                    "_value": "",
                                    "_type": "a",
                                    "_attrDef": "p",
                                    "_visibility": false
                                },
                                {
                                    "_key": "(videoplay)",
                                    "_value": "",
                                    "_type": "a",
                                    "_attrDef": "p",
                                    "_visibility": false
                                },
                                {
                                    "_key": "(audiopause)",
                                    "_value": "",
                                    "_type": "kv",
                                    "_attrDef": "p",
                                    "_visibility": false
                                },
                                {
                                    "_key": "(videopause)",
                                    "_value": "",
                                    "_type": "kv",
                                    "_attrDef": "p",
                                    "_visibility": false
                                },
                                {
                                    "_key": "(audioended)",
                                    "_value": "",
                                    "_type": "kv",
                                    "_attrDef": "p",
                                    "_visibility": false
                                },
                                {
                                    "_key": "(videoended)",
                                    "_value": "",
                                    "_type": "kv",
                                    "_attrDef": "p",
                                    "_visibility": false
                                }
                            ],
                            "a76f3860-c680-53a7-a9d8-368c6ad7b3b9": {
                                "paletteKey": "html-editor",
                                "parentEditorKey": "69b6f07f-6165-dc98-0e75-e218e6a04483",
                                "isAdvancedChildComponent": true,
                                "commentid": null,
                                "designerReference": [
                                    {
                                        "_key": "style",
                                        "_value": "",
                                        "_type": "kv",
                                        "_attrDef": "p"
                                    },
                                    {
                                        "_key": "class",
                                        "_value": "",
                                        "_type": "dav",
                                        "_attrDef": "p"
                                    },
                                    {
                                        "_key": "html",
                                        "_value": "{{data?.viewTitle === 'Residential Address' ?  page.locales.keys.residentialAdd : (data?.viewTitle === 'Company Name and Business Address' ? page.locales.keys.companyAddress : (data?.viewTitle === 'Current Address' ? page.locales.keys.currentAddress : (data?.viewTitle === 'Registration of Auto Bank Transfer' ? page.locales.keys.bankDetails : null)))}}",
                                        "_type": "a",
                                        "_attrDef": "p"
                                    }
                                ]
                            }
                        }
                    },
                    "8d89d3c9-c382-f72a-24d5-8e30aab379bd": {
                        "paletteKey": "FlexLayoutRow",
                        "parentEditorKey": "a35f3fd1-9006-84c9-7852-3a054b061809",
                        "commentid": null,
                        "designerReference": [
                            {
                                "_key": "componentLabel",
                                "_value": "Row",
                                "_type": "kv",
                                "_attrDef": "p",
                                "_useAsLabel": true
                            },
                            {
                                "_key": "style",
                                "_value": "",
                                "_type": "kv",
                                "_attrDef": "p"
                            },
                            {
                                "_key": "class",
                                "_value": [
                                    "width-100"
                                ],
                                "_type": "dav",
                                "_attrDef": "p"
                            },
                            {
                                "_key": "fxFlex",
                                "_value": "",
                                "_type": "kv",
                                "_attrDef": "p"
                            },
                            {
                                "_key": "fxLayoutGap",
                                "_value": "",
                                "_type": "kv",
                                "_attrDef": "p"
                            },
                            {
                                "_key": "wrap",
                                "_value": "wrap",
                                "_type": "a",
                                "_attrDef": "p"
                            },
                            {
                                "_key": "layoutAlign",
                                "_value": "start",
                                "_type": "a",
                                "_attrDef": "p"
                            },
                            {
                                "_key": "pLayoutAlign",
                                "_value": "stretch",
                                "_type": "a",
                                "_attrDef": "p"
                            },
                            {
                                "_key": "[fxShow]",
                                "_value": "true",
                                "_type": "kv",
                                "_attrDef": "p"
                            }
                        ],
                        "6a458a64-f6a7-1e62-c948-405ab6252c7a": {
                            "paletteKey": "FlexLayoutRow",
                            "parentEditorKey": "8d89d3c9-c382-f72a-24d5-8e30aab379bd",
                            "commentid": null,
                            "designerReference": [
                                {
                                    "_key": "componentLabel",
                                    "_value": "Row",
                                    "_type": "kv",
                                    "_attrDef": "p",
                                    "_useAsLabel": true
                                },
                                {
                                    "_key": "style",
                                    "_value": "",
                                    "_type": "kv",
                                    "_attrDef": "p"
                                },
                                {
                                    "_key": "class",
                                    "_value": "",
                                    "_type": "dav",
                                    "_attrDef": "p"
                                },
                                {
                                    "_key": "fxFlex",
                                    "_value": "50",
                                    "_type": "kv",
                                    "_attrDef": "p"
                                },
                                {
                                    "_key": "fxLayoutGap",
                                    "_value": "",
                                    "_type": "kv",
                                    "_attrDef": "p"
                                },
                                {
                                    "_key": "wrap",
                                    "_value": "wrap",
                                    "_type": "a",
                                    "_attrDef": "p"
                                },
                                {
                                    "_key": "layoutAlign",
                                    "_value": "start",
                                    "_type": "a",
                                    "_attrDef": "p"
                                },
                                {
                                    "_key": "pLayoutAlign",
                                    "_value": "center",
                                    "_type": "a",
                                    "_attrDef": "p"
                                },
                                {
                                    "_key": "[fxShow]",
                                    "_value": "true",
                                    "_type": "kv",
                                    "_attrDef": "p"
                                },
                                {
                                    "_key": "*ngFor",
                                    "_value": "let item of getAddressKeys()",
                                    "_type": "kv",
                                    "_attrDef": "c"
                                }
                            ],
                            "d64c2d7f-5afe-d967-d1f6-c81350835eae": {
                                "paletteKey": "NG-Input",
                                "parentEditorKey": "6a458a64-f6a7-1e62-c948-405ab6252c7a",
                                "isAdvancedComponent": true,
                                "commentid": null,
                                "designerReference": [
                                    {
                                        "_key": "style",
                                        "_value": "",
                                        "_type": "kv",
                                        "_attrDef": "p"
                                    },
                                    {
                                        "_key": "class",
                                        "_value": "",
                                        "_type": "dav",
                                        "_attrDef": "p"
                                    },
                                    {
                                        "_key": "placeholder",
                                        "_value": "{{page.labels[item]?.label}}",
                                        "_type": "kv",
                                        "_attrDef": "p",
                                        "_useAsLabel": true
                                    },
                                    {
                                        "_key": "value",
                                        "_value": "",
                                        "_type": "kv",
                                        "_attrDef": "p"
                                    },
                                    {
                                        "_key": "[appearance]",
                                        "_value": "'legacy'",
                                        "_type": "a",
                                        "_attrDef": "p"
                                    },
                                    {
                                        "_key": "[required]",
                                        "_value": "false",
                                        "_type": "kv",
                                        "_attrDef": "p"
                                    },
                                    {
                                        "_key": "[(ngModel)]",
                                        "_value": "",
                                        "_type": "kv",
                                        "_attrDef": "p"
                                    },
                                    {
                                        "_key": "color",
                                        "_value": "",
                                        "_type": "kv",
                                        "_attrDef": "p"
                                    },
                                    {
                                        "_key": "name",
                                        "_value": "",
                                        "_type": "kv",
                                        "_attrDef": "p"
                                    },
                                    {
                                        "_key": "type",
                                        "_value": "",
                                        "_type": "kv",
                                        "_attrDef": "p"
                                    },
                                    {
                                        "_key": "[formControl]",
                                        "_value": "",
                                        "_type": "kv",
                                        "_attrDef": "p"
                                    },
                                    {
                                        "_key": "readonly",
                                        "_value": "true",
                                        "_type": "kv",
                                        "_attrDef": "p"
                                    },
                                    {
                                        "_key": "[disabled]",
                                        "_value": "",
                                        "_type": "kv",
                                        "_attrDef": "p"
                                    },
                                    {
                                        "_key": "id",
                                        "_value": "",
                                        "_type": "kv",
                                        "_attrDef": "p"
                                    },
                                    {
                                        "_key": "[floatLabel]",
                                        "_value": "'auto'",
                                        "_type": "kv",
                                        "_attrDef": "p"
                                    },
                                    {
                                        "_key": "[hideRequiredMarker]",
                                        "_value": "false",
                                        "_type": "kv",
                                        "_attrDef": "p",
                                        "_complexity": "advanced"
                                    },
                                    {
                                        "_key": "matError",
                                        "_value": [],
                                        "_type": "a",
                                        "_attrDef": "p",
                                        "_visibility": true
                                    },
                                    {
                                        "_key": "inputHint",
                                        "_value": [],
                                        "_type": "a",
                                        "_attrDef": "p",
                                        "_visibility": true
                                    },
                                    {
                                        "_key": "Label",
                                        "_value": "",
                                        "_type": "a",
                                        "_attrDef": "p",
                                        "_visibility": true
                                    },
                                    {
                                        "_key": "Suffix Icon",
                                        "_value": "",
                                        "_type": "a",
                                        "_attrDef": "p",
                                        "_visibility": true
                                    },
                                    {
                                        "_key": "(suffixIconClick)",
                                        "_value": "",
                                        "_type": "a",
                                        "_attrDef": "p",
                                        "_visibility": true
                                    },
                                    {
                                        "_key": "Prefix Icon",
                                        "_value": "",
                                        "_type": "a",
                                        "_attrDef": "p",
                                        "_visibility": true
                                    },
                                    {
                                        "_key": "(prefixIconClick)",
                                        "_value": "",
                                        "_type": "a",
                                        "_attrDef": "p",
                                        "_visibility": true
                                    },
                                    {
                                        "_key": "Prefix",
                                        "_value": "",
                                        "_type": "a",
                                        "_attrDef": "p",
                                        "_visibility": true
                                    },
                                    {
                                        "_key": "Suffix",
                                        "_value": "",
                                        "_type": "a",
                                        "_attrDef": "p",
                                        "_visibility": true
                                    },
                                    {
                                        "_key": "[value]",
                                        "_value": "data.details[item]",
                                        "_type": "kv",
                                        "_attrDef": "c"
                                    }
                                ]
                            }
                        }
                    }
                }
            }
        }
    }
}
